eox_core/__init__.py
eox_core/admin.py
eox_core/api_schema.py
eox_core/apps.py
eox_core/logging.py
eox_core/middleware.py
eox_core/models.py
eox_core/pipeline.py
eox_core/social_tpa_backends.py
eox_core/storage.py
eox_core/test_utils.py
eox_core/urls.py
eox_core/utils.py
eox_core/views.py
eox_core/api/__init__.py
eox_core/api/urls.py
eox_core/api/data/__init__.py
eox_core/api/data/aggregated_collector/__init__.py
eox_core/api/data/aggregated_collector/queries.py
eox_core/api/data/aggregated_collector/tasks.py
eox_core/api/data/aggregated_collector/urls.py
eox_core/api/data/aggregated_collector/utils.py
eox_core/api/data/aggregated_collector/v1/__init__.py
eox_core/api/data/aggregated_collector/v1/permissions.py
eox_core/api/data/aggregated_collector/v1/urls.py
eox_core/api/data/aggregated_collector/v1/views.py
eox_core/api/data/aggregated_collector/v1/tests/__init__.py
eox_core/api/data/aggregated_collector/v1/tests/test_utils.py
eox_core/api/data/aggregated_collector/v1/tests/test_views.py
eox_core/api/data/v1/__init__.py
eox_core/api/data/v1/fields.py
eox_core/api/data/v1/filters.py
eox_core/api/data/v1/paginators.py
eox_core/api/data/v1/routers.py
eox_core/api/data/v1/serializers.py
eox_core/api/data/v1/tasks.py
eox_core/api/data/v1/urls.py
eox_core/api/data/v1/views.py
eox_core/api/data/v1/viewsets.py
eox_core/api/support/__init__.py
eox_core/api/support/urls.py
eox_core/api/support/v1/__init__.py
eox_core/api/support/v1/authentication.py
eox_core/api/support/v1/permissions.py
eox_core/api/support/v1/serializers.py
eox_core/api/support/v1/urls.py
eox_core/api/support/v1/views.py
eox_core/api/support/v1/tests/__init__.py
eox_core/api/support/v1/tests/integration/__init__.py
eox_core/api/support/v1/tests/integration/test_views.py
eox_core/api/support/v1/tests/unit/__init__.py
eox_core/api/support/v1/tests/unit/test_oauth_applications.py
eox_core/api/support/v1/tests/unit/test_permissions.py
eox_core/api/support/v1/tests/unit/test_users.py
eox_core-12.1.0.dist-info/licenses/AUTHORS.txt
eox_core-12.1.0.dist-info/licenses/LICENSE.txt
eox_core-12.1.0.dist-info/METADATA
eox_core-12.1.0.dist-info/WHEEL
eox_core-12.1.0.dist-info/entry_points.txt
eox_core-12.1.0.dist-info/top_level.txt
eox_core-12.1.0.dist-info/RECORD
