Metadata-Version: 2.4
Name: eox-core
Version: 12.1.0
Summary: eduNEXT Openedx extensions
Home-page: https://github.com/eduNEXT/eox-core
Author: eduNEXT
Author-email: contact@edunext.co
License: AGPL
Platform: any
Classifier: Development Status :: 5 - Production/Stable
Classifier: Framework :: Django :: 4.2
Classifier: Intended Audience :: Developers
Classifier: License :: OSI Approved :: GNU Affero General Public License v3
Classifier: Operating System :: OS Independent
Classifier: Programming Language :: Python :: 3.11
Requires-Python: >=3.11
License-File: LICENSE.txt
License-File: AUTHORS.txt
Requires-Dist: celery
Requires-Dist: click
Requires-Dist: django
Requires-Dist: django-filter
Requires-Dist: edx-drf-extensions
Requires-Dist: djangorestframework
Requires-Dist: six
Requires-Dist: django-oauth-toolkit
Requires-Dist: openedx-events
Requires-Dist: django-waffle
Requires-Dist: edx-proctoring>=2.0.1
Requires-Dist: edx-api-doc-tools
Requires-Dist: social-auth-core
Requires-Dist: django-oauth2-provider
Provides-Extra: sentry
Requires-Dist: sentry-sdk==1.5.1; extra == "sentry"
Provides-Extra: tpa
Requires-Dist: social-auth-core[openidconnect]; extra == "tpa"
Provides-Extra: eox-audit
Requires-Dist: eox-audit-model; extra == "eox-audit"
Dynamic: author
Dynamic: author-email
Dynamic: classifier
Dynamic: description
Dynamic: description-content-type
Dynamic: home-page
Dynamic: license
Dynamic: license-file
Dynamic: platform
Dynamic: provides-extra
Dynamic: requires-dist
Dynamic: requires-python
Dynamic: summary
